snowdev/__init__.py
snowdev/cli/__init__.py
snowdev/cli/commands.py
snowdev/cli/main.py
snowdev/deployment.py
snowdev/fillers/__init__.py
snowdev/fillers/actions.yml
snowdev/fillers/pyproject.toml
snowdev/fillers/sproc/__init__.py
snowdev/fillers/sproc/fill.py
snowdev/fillers/sproc/fill.toml
snowdev/fillers/streamlit/__init__.py
snowdev/fillers/streamlit/fill.py
snowdev/fillers/streamlit/fill.yml
snowdev/fillers/task/fill.sql
snowdev/fillers/udf/__init__.py
snowdev/fillers/udf/fill.py
snowdev/fillers/udf/fill.toml
snowdev/functions/__init__.py
snowdev/functions/bot.py
snowdev/functions/connect.py
snowdev/functions/helper.py
snowdev/functions/package_zip.py
snowdev/functions/register.py
snowdev/functions/streamlit.py
snowdev/functions/task.py
snowdev/functions/utils/__init__.py
snowdev/functions/utils/ingest.py
snowdev/functions/utils/knowledge/documentation.md
snowdev/functions/utils/knowledge/sproc.py
snowdev/functions/utils/knowledge/streamlit_app.py
snowdev/functions/utils/knowledge/task.md
snowdev/functions/utils/knowledge/udf.py
snowdev/functions/utils/snowpark_methods.py
snowdev/functions/utils/templates/sproc.py
snowdev/functions/utils/templates/streamlit.py
snowdev/functions/utils/templates/task.py
snowdev/functions/utils/templates/udf.py
snowdev-0.2.0.dist-info/METADATA
snowdev-0.2.0.dist-info/WHEEL
snowdev-0.2.0.dist-info/entry_points.txt
snowdev-0.2.0.dist-info/RECORD
