Metadata-Version: 2.1
Name: snowdev
Version: 0.2.0
Summary: snowdev: DevOps toolkit for Snowflake, facilitating seamless deployment of UDFs, stored procedures, and Streamlit apps using Snowpark's capabilities right from your local environment.
Home-page: https://github.com/kaarthik108/snowdev
Author: kaarthik
Author-email: kaarthikandavar@gmail.com
Requires-Python: >=3.10.0,<3.11.0
Classifier: Development Status :: 4 - Beta
Classifier: Intended Audience :: Developers
Classifier: License :: OSI Approved :: MIT License
Classifier: Programming Language :: Python :: 3
Classifier: Programming Language :: Python :: 3.10
Requires-Dist: chromadb (==0.4.6)
Requires-Dist: langchain (==0.0.265)
Requires-Dist: openai (>=0.27.8,<0.28.0)
Requires-Dist: pydantic (==1.10.9)
Requires-Dist: pyyaml (>=6.0.1,<7.0.0)
Requires-Dist: snowflake-ml-python (==1.0.5)
Requires-Dist: snowflake-snowpark-python[pandas] (==1.6.1)
Requires-Dist: termcolor (==2.3.0)
Requires-Dist: tiktoken (==0.4.0)
Requires-Dist: toml (>=0.10.2,<0.11.0)
Requires-Dist: unstructured (==0.7.12)
